{
 "pg_stat_database": [
  {
   "temp_files": "0",
   "tup_returned": "164",
   "xact_commit": "0",
   "numbackends": "0",
   "session_time": "0",
   "stats_reset": null,
   "checksum_last_failure": null,
   "conflicts": "0",
   "blks_read": "90",
   "temp_bytes": "0",
   "datid": "0",
   "deadlocks": "0",
   "tup_inserted": "35",
   "sessions_fatal": "0",
   "sessions": "0",
   "blk_write_time": "0",
   "datname": null,
   "blks_hit": "701",
   "blk_read_time": "0",
   "active_time": "0",
   "sessions_killed": "0",
   "tup_fetched": "102",
   "tup_updated": "4",
   "sessions_abandoned": "0",
   "xact_rollback": "0",
   "tup_deleted": "0",
   "checksum_failures": null,
   "idle_in_transaction_time": "0"
  },
  {
   "temp_files": "0",
   "tup_returned": "3546",
   "xact_commit": "12",
   "numbackends": "0",
   "session_time": "27.897",
   "stats_reset": null,
   "checksum_last_failure": null,
   "conflicts": "0",
   "blks_read": "87",
   "temp_bytes": "0",
   "datid": "5",
   "deadlocks": "0",
   "tup_inserted": "0",
   "sessions_fatal": "0",
   "sessions": "2",
   "blk_write_time": "0",
   "datname": "postgres",
   "blks_hit": "1864",
   "blk_read_time": "0",
   "active_time": "40.996",
   "sessions_killed": "0",
   "tup_fetched": "881",
   "tup_updated": "0",
   "sessions_abandoned": "0",
   "xact_rollback": "0",
   "tup_deleted": "0",
   "checksum_failures": null,
   "idle_in_transaction_time": "0"
  },
  {
   "temp_files": "0",
   "tup_returned": "1366875",
   "xact_commit": "10587",
   "numbackends": "1",
   "session_time": "104245.797",
   "stats_reset": null,
   "checksum_last_failure": null,
   "conflicts": "0",
   "blks_read": "15569",
   "temp_bytes": "0",
   "datid": "16385",
   "deadlocks": "0",
   "tup_inserted": "634219",
   "sessions_fatal": "0",
   "sessions": "6",
   "blk_write_time": "0",
   "datname": "benchbase",
   "blks_hit": "10260902",
   "blk_read_time": "0",
   "active_time": "43477.272",
   "sessions_killed": "0",
   "tup_fetched": "1279642",
   "tup_updated": "65317",
   "sessions_abandoned": "0",
   "xact_rollback": "15",
   "tup_deleted": "2381",
   "checksum_failures": null,
   "idle_in_transaction_time": "42575.62"
  },
  {
   "temp_files": "0",
   "tup_returned": "73141",
   "xact_commit": "904",
   "numbackends": "0",
   "session_time": "0",
   "stats_reset": null,
   "checksum_last_failure": null,
   "conflicts": "0",
   "blks_read": "1046",
   "temp_bytes": "0",
   "datid": "1",
   "deadlocks": "0",
   "tup_inserted": "15965",
   "sessions_fatal": "0",
   "sessions": "0",
   "blk_write_time": "0",
   "datname": "template1",
   "blks_hit": "77481",
   "blk_read_time": "0",
   "active_time": "0",
   "sessions_killed": "0",
   "tup_fetched": "25937",
   "tup_updated": "732",
   "sessions_abandoned": "0",
   "xact_rollback": "0",
   "tup_deleted": "34",
   "checksum_failures": null,
   "idle_in_transaction_time": "0"
  },
  {
   "temp_files": "0",
   "tup_returned": "0",
   "xact_commit": "0",
   "numbackends": "0",
   "session_time": "0",
   "stats_reset": null,
   "checksum_last_failure": null,
   "conflicts": "0",
   "blks_read": "0",
   "temp_bytes": "0",
   "datid": "4",
   "deadlocks": "0",
   "tup_inserted": "0",
   "sessions_fatal": "0",
   "sessions": "0",
   "blk_write_time": "0",
   "datname": "template0",
   "blks_hit": "0",
   "blk_read_time": "0",
   "active_time": "0",
   "sessions_killed": "0",
   "tup_fetched": "0",
   "tup_updated": "0",
   "sessions_abandoned": "0",
   "xact_rollback": "0",
   "tup_deleted": "0",
   "checksum_failures": null,
   "idle_in_transaction_time": "0"
  }
 ],
 "pg_stat_user_indexes": [
  {
   "indexrelname": "warehouse_pkey",
   "relname": "warehouse",
   "relid": "16390",
   "schemaname": "public",
   "idx_tup_read": "103621",
   "idx_tup_fetch": "103621",
   "idx_scan": "103621",
   "indexrelid": "16393"
  },
  {
   "indexrelname": "item_pkey",
   "relname": "item",
   "relid": "16395",
   "schemaname": "public",
   "idx_tup_read": "126889",
   "idx_tup_fetch": "126889",
   "idx_scan": "126904",
   "indexrelid": "16398"
  },
  {
   "indexrelname": "stock_pkey",
   "relname": "stock",
   "relid": "16400",
   "schemaname": "public",
   "idx_tup_read": "428188",
   "idx_tup_fetch": "425008",
   "idx_scan": "425008",
   "indexrelid": "16403"
  },
  {
   "indexrelname": "district_pkey",
   "relname": "district",
   "relid": "16415",
   "schemaname": "public",
   "idx_tup_read": "66223",
   "idx_tup_fetch": "66223",
   "idx_scan": "66223",
   "indexrelid": "16418"
  },
  {
   "indexrelname": "customer_pkey",
   "relname": "customer",
   "relid": "16425",
   "schemaname": "public",
   "idx_tup_read": "99146",
   "idx_tup_fetch": "97867",
   "idx_scan": "73875",
   "indexrelid": "16431"
  },
  {
   "indexrelname": "oorder_pkey",
   "relname": "oorder",
   "relid": "16452",
   "schemaname": "public",
   "idx_tup_read": "17617",
   "idx_tup_fetch": "17617",
   "idx_scan": "17617",
   "indexrelid": "16456"
  },
  {
   "indexrelname": "oorder_o_w_id_o_d_id_o_c_id_o_id_key",
   "relname": "oorder",
   "relid": "16452",
   "schemaname": "public",
   "idx_tup_read": "325709",
   "idx_tup_fetch": "325707",
   "idx_scan": "325707",
   "indexrelid": "16458"
  },
  {
   "indexrelname": "new_order_pkey",
   "relname": "new_order",
   "relid": "16465",
   "schemaname": "public",
   "idx_tup_read": "6954",
   "idx_tup_fetch": "4644",
   "idx_scan": "4660",
   "indexrelid": "16468"
  },
  {
   "indexrelname": "order_line_pkey",
   "relname": "order_line",
   "relid": "16475",
   "schemaname": "public",
   "idx_tup_read": "100637",
   "idx_tup_fetch": "94711",
   "idx_scan": "5115",
   "indexrelid": "16478"
  },
  {
   "indexrelname": "idx_customer_name",
   "relname": "customer",
   "relid": "16425",
   "schemaname": "public",
   "idx_tup_read": "5891",
   "idx_tup_fetch": "5711",
   "idx_scan": "1592",
   "indexrelid": "16490"
  }
 ],
 "pg_statio_user_tables": [
  {
   "idx_blks_read": "2",
   "relname": "warehouse",
   "heap_blks_hit": "215001",
   "relid": "16390",
   "schemaname": "public",
   "tidx_blks_read": null,
   "heap_blks_read": "1",
   "tidx_blks_hit": null,
   "idx_blks_hit": "103625",
   "toast_blks_hit": null,
   "toast_blks_read": null
  },
  {
   "idx_blks_read": "276",
   "relname": "stock",
   "heap_blks_hit": "1505605",
   "relid": "16400",
   "schemaname": "public",
   "tidx_blks_read": null,
   "heap_blks_read": "4502",
   "tidx_blks_hit": null,
   "idx_blks_hit": "1060256",
   "toast_blks_hit": null,
   "toast_blks_read": null
  },
  {
   "idx_blks_read": "276",
   "relname": "item",
   "heap_blks_hit": "333395",
   "relid": "16395",
   "schemaname": "public",
   "tidx_blks_read": null,
   "heap_blks_read": "1275",
   "tidx_blks_hit": null,
   "idx_blks_hit": "453679",
   "toast_blks_hit": null,
   "toast_blks_read": null
  },
  {
   "idx_blks_read": "2",
   "relname": "district",
   "heap_blks_hit": "153400",
   "relid": "16415",
   "schemaname": "public",
   "tidx_blks_read": null,
   "heap_blks_read": "1",
   "tidx_blks_hit": null,
   "idx_blks_hit": "66236",
   "toast_blks_hit": null,
   "toast_blks_read": null
  },
  {
   "idx_blks_read": "396",
   "relname": "customer",
   "heap_blks_hit": "294141",
   "relid": "16425",
   "schemaname": "public",
   "tidx_blks_read": "0",
   "heap_blks_read": "2393",
   "tidx_blks_hit": "0",
   "idx_blks_hit": "290328",
   "toast_blks_hit": "0",
   "toast_blks_read": "0"
  },
  {
   "idx_blks_read": null,
   "relname": "history",
   "heap_blks_hit": "99043",
   "relid": "16438",
   "schemaname": "public",
   "tidx_blks_read": null,
   "heap_blks_read": "347",
   "tidx_blks_hit": null,
   "idx_blks_hit": null,
   "toast_blks_hit": null,
   "toast_blks_read": null
  },
  {
   "idx_blks_read": "306",
   "relname": "oorder",
   "heap_blks_hit": "756843",
   "relid": "16452",
   "schemaname": "public",
   "tidx_blks_read": null,
   "heap_blks_read": "269",
   "tidx_blks_hit": null,
   "idx_blks_hit": "3248802",
   "toast_blks_hit": null,
   "toast_blks_read": null
  },
  {
   "idx_blks_read": "49",
   "relname": "new_order",
   "heap_blks_hit": "31892",
   "relid": "16465",
   "schemaname": "public",
   "tidx_blks_read": null,
   "heap_blks_read": "60",
   "tidx_blks_hit": null,
   "idx_blks_hit": "33321",
   "toast_blks_hit": null,
   "toast_blks_read": null
  },
  {
   "idx_blks_read": "1268",
   "relname": "order_line",
   "heap_blks_hit": "1104304",
   "relid": "16475",
   "schemaname": "public",
   "tidx_blks_read": null,
   "heap_blks_read": "4096",
   "tidx_blks_hit": null,
   "idx_blks_hit": "491380",
   "toast_blks_hit": null,
   "toast_blks_read": null
  }
 ],
 "pg_stat_bgwriter": [{
  "checkpoint_write_time": "0",
  "buffers_backend_fsync": "0",
  "buffers_clean": "620",
  "checkpoints_req": "0",
  "checkpoint_sync_time": "0",
  "stats_reset": "2023-09-06 14:26:12.712549+00",
  "buffers_checkpoint": "0",
  "checkpoints_timed": "0",
  "buffers_alloc": "17367",
  "buffers_backend": "15765",
  "maxwritten_clean": "0"
 }],
 "pg_stat_user_tables": [
  {
   "n_tup_upd": "2451",
   "n_ins_since_vacuum": "1",
   "relname": "warehouse",
   "analyze_count": "0",
   "n_tup_del": "0",
   "relid": "16390",
   "schemaname": "public",
   "n_tup_ins": "1",
   "last_autoanalyze": "2023-09-06 14:29:13.670616+00",
   "last_autovacuum": null,
   "last_analyze": null,
   "n_mod_since_analyze": "1272",
   "idx_tup_fetch": "103621",
   "seq_tup_read": "3987",
   "vacuum_count": "0",
   "autoanalyze_count": "1",
   "autovacuum_count": "0",
   "n_live_tup": "1",
   "n_dead_tup": "44",
   "last_vacuum": null,
   "n_tup_hot_upd": "2451",
   "seq_scan": "3988",
   "idx_scan": "103621"
  },
  {
   "n_tup_upd": "0",
   "n_ins_since_vacuum": "1230",
   "relname": "history",
   "analyze_count": "0",
   "n_tup_del": "0",
   "relid": "16438",
   "schemaname": "public",
   "n_tup_ins": "32451",
   "last_autoanalyze": "2023-09-06 14:29:14.766775+00",
   "last_autovacuum": "2023-09-06 14:29:14.696218+00",
   "last_analyze": null,
   "n_mod_since_analyze": "1230",
   "idx_tup_fetch": null,
   "seq_tup_read": "0",
   "vacuum_count": "0",
   "autoanalyze_count": "1",
   "autovacuum_count": "1",
   "n_live_tup": "32460",
   "n_dead_tup": "0",
   "last_vacuum": null,
   "n_tup_hot_upd": "0",
   "seq_scan": "0",
   "idx_scan": null
  },
  {
   "n_tup_upd": "5118",
   "n_ins_since_vacuum": "10",
   "relname": "district",
   "analyze_count": "0",
   "n_tup_del": "0",
   "relid": "16415",
   "schemaname": "public",
   "n_tup_ins": "10",
   "last_autoanalyze": "2023-09-06 14:29:14.175426+00",
   "last_autovacuum": null,
   "last_analyze": null,
   "n_mod_since_analyze": "2723",
   "idx_tup_fetch": "66223",
   "seq_tup_read": "64733",
   "vacuum_count": "0",
   "autoanalyze_count": "1",
   "autovacuum_count": "0",
   "n_live_tup": "10",
   "n_dead_tup": "66",
   "last_vacuum": null,
   "n_tup_hot_upd": "5118",
   "seq_scan": "6686",
   "idx_scan": "66223"
  },
  {
   "n_tup_upd": "23863",
   "n_ins_since_vacuum": "14257",
   "relname": "order_line",
   "analyze_count": "0",
   "n_tup_del": "0",
   "relid": "16475",
   "schemaname": "public",
   "n_tup_ins": "326763",
   "last_autoanalyze": "2023-09-06 14:29:15.100214+00",
   "last_autovacuum": "2023-09-06 14:29:14.955551+00",
   "last_analyze": null,
   "n_mod_since_analyze": "26204",
   "idx_tup_fetch": "94711",
   "seq_tup_read": "0",
   "vacuum_count": "0",
   "autoanalyze_count": "1",
   "autovacuum_count": "1",
   "n_live_tup": "327076",
   "n_dead_tup": "3904",
   "last_vacuum": null,
   "n_tup_hot_upd": "17940",
   "seq_scan": "1",
   "idx_scan": "5115"
  },
  {
   "n_tup_upd": "2330",
   "n_ins_since_vacuum": "1419",
   "relname": "oorder",
   "analyze_count": "0",
   "n_tup_del": "0",
   "relid": "16452",
   "schemaname": "public",
   "n_tup_ins": "32667",
   "last_autoanalyze": "2023-09-06 14:29:14.823105+00",
   "last_autovacuum": "2023-09-06 14:29:14.780704+00",
   "last_analyze": null,
   "n_mod_since_analyze": "2528",
   "idx_tup_fetch": "343324",
   "seq_tup_read": "0",
   "vacuum_count": "0",
   "autoanalyze_count": "1",
   "autovacuum_count": "1",
   "n_live_tup": "32674",
   "n_dead_tup": "233",
   "last_vacuum": null,
   "n_tup_hot_upd": "1886",
   "seq_scan": "2",
   "idx_scan": "343324"
  },
  {
   "n_tup_upd": "4781",
   "n_ins_since_vacuum": "0",
   "relname": "customer",
   "analyze_count": "0",
   "n_tup_del": "0",
   "relid": "16425",
   "schemaname": "public",
   "n_tup_ins": "30000",
   "last_autoanalyze": "2023-09-06 14:29:14.683322+00",
   "last_autovacuum": "2023-09-06 14:29:14.257601+00",
   "last_analyze": null,
   "n_mod_since_analyze": "2350",
   "idx_tup_fetch": "103578",
   "seq_tup_read": "0",
   "vacuum_count": "0",
   "autoanalyze_count": "2",
   "autovacuum_count": "2",
   "n_live_tup": "30000",
   "n_dead_tup": "1447",
   "last_vacuum": null,
   "n_tup_hot_upd": "2275",
   "seq_scan": "2",
   "idx_scan": "75467"
  },
  {
   "n_tup_upd": "0",
   "n_ins_since_vacuum": "1419",
   "relname": "new_order",
   "analyze_count": "0",
   "n_tup_del": "2330",
   "relid": "16465",
   "schemaname": "public",
   "n_tup_ins": "11667",
   "last_autoanalyze": "2023-09-06 14:29:14.830949+00",
   "last_autovacuum": "2023-09-06 14:29:14.827763+00",
   "last_analyze": null,
   "n_mod_since_analyze": "2528",
   "idx_tup_fetch": "4644",
   "seq_tup_read": "0",
   "vacuum_count": "0",
   "autoanalyze_count": "1",
   "autovacuum_count": "1",
   "n_live_tup": "9326",
   "n_dead_tup": "1131",
   "last_vacuum": null,
   "n_tup_hot_upd": "0",
   "seq_scan": "1",
   "idx_scan": "4660"
  },
  {
   "n_tup_upd": "26723",
   "n_ins_since_vacuum": "0",
   "relname": "stock",
   "analyze_count": "0",
   "n_tup_del": "0",
   "relid": "16400",
   "schemaname": "public",
   "n_tup_ins": "100000",
   "last_autoanalyze": "2023-09-06 14:29:14.172109+00",
   "last_autovacuum": "2023-09-06 14:28:13.752525+00",
   "last_analyze": null,
   "n_mod_since_analyze": "14687",
   "idx_tup_fetch": "425008",
   "seq_tup_read": "0",
   "vacuum_count": "0",
   "autoanalyze_count": "2",
   "autovacuum_count": "1",
   "n_live_tup": "100000",
   "n_dead_tup": "4444",
   "last_vacuum": null,
   "n_tup_hot_upd": "23125",
   "seq_scan": "1",
   "idx_scan": "425008"
  },
  {
   "n_tup_upd": "0",
   "n_ins_since_vacuum": "0",
   "relname": "item",
   "analyze_count": "0",
   "n_tup_del": "0",
   "relid": "16395",
   "schemaname": "public",
   "n_tup_ins": "100000",
   "last_autoanalyze": "2023-09-06 14:28:14.389212+00",
   "last_autovacuum": "2023-09-06 14:28:14.279629+00",
   "last_analyze": null,
   "n_mod_since_analyze": "0",
   "idx_tup_fetch": "126889",
   "seq_tup_read": "0",
   "vacuum_count": "0",
   "autoanalyze_count": "1",
   "autovacuum_count": "1",
   "n_live_tup": "100000",
   "n_dead_tup": "0",
   "last_vacuum": null,
   "n_tup_hot_upd": "0",
   "seq_scan": "1",
   "idx_scan": "126904"
  }
 ],
 "pg_statio_user_indexes": [
  {
   "idx_blks_read": "2",
   "indexrelname": "warehouse_pkey",
   "relname": "warehouse",
   "relid": "16390",
   "schemaname": "public",
   "idx_blks_hit": "103625",
   "indexrelid": "16393"
  },
  {
   "idx_blks_read": "276",
   "indexrelname": "item_pkey",
   "relname": "item",
   "relid": "16395",
   "schemaname": "public",
   "idx_blks_hit": "453679",
   "indexrelid": "16398"
  },
  {
   "idx_blks_read": "276",
   "indexrelname": "stock_pkey",
   "relname": "stock",
   "relid": "16400",
   "schemaname": "public",
   "idx_blks_hit": "1060256",
   "indexrelid": "16403"
  },
  {
   "idx_blks_read": "2",
   "indexrelname": "district_pkey",
   "relname": "district",
   "relid": "16415",
   "schemaname": "public",
   "idx_blks_hit": "66236",
   "indexrelid": "16418"
  },
  {
   "idx_blks_read": "117",
   "indexrelname": "customer_pkey",
   "relname": "customer",
   "relid": "16425",
   "schemaname": "public",
   "idx_blks_hit": "213088",
   "indexrelid": "16431"
  },
  {
   "idx_blks_read": "133",
   "indexrelname": "oorder_pkey",
   "relname": "oorder",
   "relid": "16452",
   "schemaname": "public",
   "idx_blks_hit": "101441",
   "indexrelid": "16456"
  },
  {
   "idx_blks_read": "173",
   "indexrelname": "oorder_o_w_id_o_d_id_o_c_id_o_id_key",
   "relname": "oorder",
   "relid": "16452",
   "schemaname": "public",
   "idx_blks_hit": "3147361",
   "indexrelid": "16458"
  },
  {
   "idx_blks_read": "49",
   "indexrelname": "new_order_pkey",
   "relname": "new_order",
   "relid": "16465",
   "schemaname": "public",
   "idx_blks_hit": "33321",
   "indexrelid": "16468"
  },
  {
   "idx_blks_read": "1268",
   "indexrelname": "order_line_pkey",
   "relname": "order_line",
   "relid": "16475",
   "schemaname": "public",
   "idx_blks_hit": "491380",
   "indexrelid": "16478"
  },
  {
   "idx_blks_read": "279",
   "indexrelname": "idx_customer_name",
   "relname": "customer",
   "relid": "16425",
   "schemaname": "public",
   "idx_blks_hit": "77240",
   "indexrelid": "16490"
  }
 ],
 "pg_stat_archiver": [{
  "last_failed_wal": null,
  "archived_count": "0",
  "last_archived_wal": null,
  "stats_reset": "2023-09-06 14:26:12.712549+00",
  "last_archived_time": null,
  "failed_count": "0",
  "last_failed_time": null
 }],
 "pg_stat_database_conflicts": [
  {
   "confl_tablespace": "0",
   "confl_deadlock": "0",
   "datname": "postgres",
   "confl_lock": "0",
   "datid": "5",
   "confl_bufferpin": "0",
   "confl_snapshot": "0"
  },
  {
   "confl_tablespace": "0",
   "confl_deadlock": "0",
   "datname": "benchbase",
   "confl_lock": "0",
   "datid": "16385",
   "confl_bufferpin": "0",
   "confl_snapshot": "0"
  },
  {
   "confl_tablespace": "0",
   "confl_deadlock": "0",
   "datname": "template1",
   "confl_lock": "0",
   "datid": "1",
   "confl_bufferpin": "0",
   "confl_snapshot": "0"
  },
  {
   "confl_tablespace": "0",
   "confl_deadlock": "0",
   "datname": "template0",
   "confl_lock": "0",
   "datid": "4",
   "confl_bufferpin": "0",
   "confl_snapshot": "0"
  }
 ]
}